scoredraft_editor/__init__.py
scoredraft_editor-0.0.4.dist-info/METADATA
scoredraft_editor-0.0.4.dist-info/WHEEL
scoredraft_editor-0.0.4.dist-info/entry_points.txt
scoredraft_editor-0.0.4.dist-info/top_level.txt
scoredraft_editor-0.0.4.dist-info/RECORD
