Metadata-Version: 2.1
Name: scoredraft-editor
Version: 0.0.4
Summary: Commandline Utilities for ScoreDraftEditor
Home-page: https://github.com/fynv/ScoreDraftEditor
Author: Fei Yang, Vulcan Eon, Beijing
Author-email: hyangfeih@gmail.com
License: MIT
Keywords: synthesizer audio music utau psola
Platform: UNKNOWN
Requires-Dist: scoredraft (>=1.0.6)
